json_server/__init__.py
json_server/cli.py
json_server/handlers.py
json_server_py-0.1.11.dist-info/entry_points.txt
json_server_py-0.1.11.dist-info/WHEEL
json_server_py-0.1.11.dist-info/METADATA
json_server_py-0.1.11.dist-info/RECORD
