Metadata-Version: 2.1
Name: json-server-py
Version: 0.1.11
Summary: A simple JSON server
Home-page: https://github.com/gera2ld/json-server.py
License: MIT
Author: Gerald
Author-email: gera2ld@live.com
Requires-Python: >=3.6,<4.0
Classifier: License :: OSI Approved :: MIT License
Classifier: Programming Language :: Python :: 3
Classifier: Programming Language :: Python :: 3.6
Classifier: Programming Language :: Python :: 3.7
Classifier: Programming Language :: Python :: 3.8
Classifier: Programming Language :: Python :: 3.9
Classifier: Programming Language :: Python :: 3.10
Classifier: Programming Language :: Python :: 3.11
Requires-Dist: aiohttp (>=3.8.1,<4.0.0)
Requires-Dist: click (>=8.0,<9.0)
Requires-Dist: gera2ld-pyserve (>=0.3.1,<0.4.0)
Requires-Dist: importlib_metadata (>=1.7.0,<2.0.0)
Project-URL: Repository, https://github.com/gera2ld/json-server.py
